{
  "sections": {
    "main": {
      "type": "main-page",
      "disabled": true,
      "settings": {
        "padding_top": 12,
        "padding_bottom": 0
      }
    },
    "pop_up_BPtt7U": {
      "type": "pop-up",
      "custom_css": [
        "img {width: 100%; height: 50%; padding-left: 40px; padding-right: 40px;}"
      ],
      "settings": {
        "heading": "Popup section",
        "image_desktop": "shopify:\/\/shop_images\/pexels-todd-trapani-1420440.jpg",
        "image_mobile": "shopify:\/\/shop_images\/pexels-todd-trapani-1420440_828d419b-ed09-45ad-83de-c7077a1a392a.jpg"
      }
    }
  },
  "order": [
    "main",
    "pop_up_BPtt7U"
  ]
}
